{"id":0,"company":"SMP","nodes":[{"id":"broccole carmine joseph","label":"broccole carmine joseph","degree":6,"x":0.8539126449044749,"y":0.8374449052667982},{"id":"burke james j","label":"burke james j","degree":6,"x":0.6012597025763071,"y":0.44499666795815307},{"id":"burks dale","label":"burks dale","degree":6,"x":0.41550924995545946,"y":0.0},{"id":"nicholas ray","label":"nicholas ray","degree":5,"x":0.0,"y":0.9183151722881483},{"id":"sills eric","label":"sills eric","degree":6,"x":0.13781801129409413,"y":0.35139007553319124},{"id":"sills lawrence i","label":"sills lawrence i","degree":6,"x":0.477453856976826,"y":1.0},{"id":"tesoro thomas","label":"tesoro thomas","degree":5,"x":1.0,"y":0.13077174734223954}],"edges":[{"source":"broccole carmine joseph","target":"burke james j","similarity":0.898889},{"source":"broccole carmine joseph","target":"burks dale","similarity":0.923803},{"source":"broccole carmine joseph","target":"nicholas ray","similarity":0.923803},{"source":"broccole carmine joseph","target":"sills eric","similarity":0.964},{"source":"broccole carmine joseph","target":"sills lawrence i","similarity":0.781569},{"source":"broccole carmine joseph","target":"tesoro thomas","similarity":0.734283},{"source":"burke james j","target":"burks dale","similarity":0.88211},{"source":"burke james j","target":"nicholas ray","similarity":0.839385},{"source":"burke james j","target":"sills eric","similarity":0.87234},{"source":"burke james j","target":"sills lawrence i","similarity":0.795124},{"source":"burke james j","target":"tesoro thomas","similarity":0.728857},{"source":"burks dale","target":"nicholas ray","similarity":0.862069},{"source":"burks dale","target":"sills eric","similarity":0.877762},{"source":"burks dale","target":"sills lawrence i","similarity":0.718516},{"source":"burks dale","target":"tesoro thomas","similarity":0.704105},{"source":"nicholas ray","target":"sills eric","similarity":0.883047},{"source":"nicholas ray","target":"sills lawrence i","similarity":0.718516},{"source":"sills eric","target":"sills lawrence i","similarity":0.779143},{"source":"sills eric","target":"tesoro thomas","similarity":0.725149},{"source":"sills lawrence i","target":"tesoro thomas","similarity":0.73931}]}