{"id":0,"company":"PRGS","nodes":[{"id":"jarrett loren","label":"jarrett loren","degree":2,"x":1.0,"y":1.0},{"id":"folger anthony","label":"folger anthony","degree":2,"x":0.9670430689682283,"y":0.0},{"id":"ainsworth john","label":"ainsworth john","degree":3,"x":0.5391939582264788,"y":0.5869211985623548},{"id":"gupta yogesh k","label":"gupta yogesh k","degree":1,"x":0.0,"y":0.6924005512088143}],"edges":[{"source":"jarrett loren","target":"ainsworth john","similarity":0.940741},{"source":"jarrett loren","target":"folger anthony","similarity":0.766755},{"source":"folger anthony","target":"ainsworth john","similarity":0.81381},{"source":"ainsworth john","target":"gupta yogesh k","similarity":0.743787}]}