{"id":0,"company":"FMC","nodes":[{"id":"cordeiro eduardo e","label":"cordeiro eduardo e","degree":7,"x":0.5741673196179257,"y":0.9144968273047063},{"id":"greer c scott","label":"greer c scott","degree":7,"x":0.9898522762728195,"y":0.7930722919808003},{"id":"johnson klynne","label":"johnson klynne","degree":7,"x":0.2470040033727222,"y":0.14290239477103228},{"id":"kempthorne dirk a","label":"kempthorne dirk a","degree":7,"x":0.0,"y":0.4992398065934917},{"id":"norris paul j","label":"norris paul j","degree":7,"x":0.48952806897365586,"y":0.4746923285955466},{"id":"oevrum margareth","label":"oevrum margareth","degree":6,"x":0.08414338768281035,"y":1.0},{"id":"pallash robert c","label":"pallash robert c","degree":7,"x":1.0,"y":0.41966417167418607},{"id":"volpe vincent r jr","label":"volpe vincent r jr","degree":6,"x":0.8571784989886306,"y":0.0}],"edges":[{"source":"cordeiro eduardo e","target":"greer c scott","similarity":0.918403},{"source":"cordeiro eduardo e","target":"johnson klynne","similarity":0.918403},{"source":"cordeiro eduardo e","target":"kempthorne dirk a","similarity":0.918403},{"source":"cordeiro eduardo e","target":"norris paul j","similarity":0.835227},{"source":"cordeiro eduardo e","target":"oevrum margareth","similarity":0.793651},{"source":"cordeiro eduardo e","target":"pallash robert c","similarity":0.88},{"source":"cordeiro eduardo e","target":"volpe vincent r jr","similarity":0.798913},{"source":"greer c scott","target":"johnson klynne","similarity":1.0},{"source":"greer c scott","target":"kempthorne dirk a","similarity":1.0},{"source":"greer c scott","target":"norris paul j","similarity":0.909091},{"source":"greer c scott","target":"oevrum margareth","similarity":0.863636},{"source":"greer c scott","target":"pallash robert c","similarity":0.958333},{"source":"greer c scott","target":"volpe vincent r jr","similarity":0.865801},{"source":"johnson klynne","target":"kempthorne dirk a","similarity":1.0},{"source":"johnson klynne","target":"norris paul j","similarity":0.909091},{"source":"johnson klynne","target":"oevrum margareth","similarity":0.863636},{"source":"johnson klynne","target":"pallash robert c","similarity":0.958333},{"source":"johnson klynne","target":"volpe vincent r jr","similarity":0.865801},{"source":"kempthorne dirk a","target":"norris paul j","similarity":0.909091},{"source":"kempthorne dirk a","target":"oevrum margareth","similarity":0.863636},{"source":"kempthorne dirk a","target":"pallash robert c","similarity":0.958333},{"source":"kempthorne dirk a","target":"volpe vincent r jr","similarity":0.865801},{"source":"norris paul j","target":"oevrum margareth","similarity":0.708333},{"source":"norris paul j","target":"pallash robert c","similarity":0.875},{"source":"norris paul j","target":"volpe vincent r jr","similarity":0.947368},{"source":"oevrum margareth","target":"pallash robert c","similarity":0.833333},{"source":"pallash robert c","target":"volpe vincent r jr","similarity":0.835227}]}