{"id":0,"company":"SND","nodes":[{"id":"beckelman lee e","label":"beckelman lee e","degree":2,"x":0.16787328910576235,"y":1.0},{"id":"kiszka robert","label":"kiszka robert","degree":2,"x":1.0,"y":0.36255866902582407},{"id":"young william john","label":"young william john","degree":2,"x":0.0,"y":0.0}],"edges":[{"source":"beckelman lee e","target":"kiszka robert","similarity":0.827731},{"source":"beckelman lee e","target":"young william john","similarity":0.955882},{"source":"kiszka robert","target":"young william john","similarity":0.895089}]}