{"id":0,"company":"VIRT","nodes":[{"id":"viola michael t","label":"viola michael t","degree":2,"x":0.16787328910576235,"y":1.0},{"id":"viola teresa","label":"viola teresa","degree":2,"x":1.0,"y":0.36255866902582407},{"id":"viola vincent j","label":"viola vincent j","degree":2,"x":0.0,"y":0.0}],"edges":[{"source":"viola michael t","target":"viola teresa","similarity":1.0},{"source":"viola michael t","target":"viola vincent j","similarity":1.0},{"source":"viola teresa","target":"viola vincent j","similarity":1.0}]}