{"id":0,"company":"CPIX","nodes":[{"id":"cearnal martin e","label":"cearnal martin e","degree":4,"x":0.6098959615041811,"y":0.0},{"id":"jones james","label":"jones james","degree":4,"x":1.0,"y":0.5417187376495618},{"id":"kazimi a j","label":"kazimi a j","degree":3,"x":0.0,"y":0.03571090950713481},{"id":"krogulski kenneth","label":"krogulski kenneth","degree":5,"x":0.2708089990570933,"y":0.5615794008721134},{"id":"young caroline","label":"young caroline","degree":5,"x":0.5750638916624172,"y":0.39418856022554044},{"id":"galante joseph c","label":"galante joseph c","degree":3,"x":0.6964672336620092,"y":1.0}],"edges":[{"source":"cearnal martin e","target":"jones james","similarity":0.742272},{"source":"cearnal martin e","target":"kazimi a j","similarity":0.865816},{"source":"cearnal martin e","target":"krogulski kenneth","similarity":0.704586},{"source":"cearnal martin e","target":"young caroline","similarity":0.700309},{"source":"jones james","target":"galante joseph c","similarity":0.852604},{"source":"jones james","target":"krogulski kenneth","similarity":0.924658},{"source":"jones james","target":"young caroline","similarity":0.912176},{"source":"kazimi a j","target":"krogulski kenneth","similarity":0.787182},{"source":"kazimi a j","target":"young caroline","similarity":0.736078},{"source":"krogulski kenneth","target":"galante joseph c","similarity":0.938845},{"source":"krogulski kenneth","target":"young caroline","similarity":0.937952},{"source":"young caroline","target":"galante joseph c","similarity":0.88423}]}