{"id":0,"company":"ALVR","nodes":[{"id":"brainard diana","label":"brainard diana","degree":2,"x":1.0,"y":1.0},{"id":"hagen brett r","label":"hagen brett r","degree":3,"x":0.6904243347907615,"y":0.21402959838361882},{"id":"sinha vikas","label":"sinha vikas","degree":3,"x":0.3116810464078913,"y":0.7880757828150341},{"id":"miller edward","label":"miller edward","degree":2,"x":0.0,"y":0.0}],"edges":[{"source":"brainard diana","target":"hagen brett r","similarity":0.711111},{"source":"brainard diana","target":"sinha vikas","similarity":0.816739},{"source":"hagen brett r","target":"miller edward","similarity":0.782738},{"source":"hagen brett r","target":"sinha vikas","similarity":0.909524},{"source":"sinha vikas","target":"miller edward","similarity":0.755682}]}