{"id":772,"nodes":[{"id":"kao george","label":"kao george","degree":2,"companies":["SMCI"],"x":0.16787328910576235,"y":1.0},{"id":"weigand david e","label":"weigand david e","degree":2,"companies":["SMCI"],"x":1.0,"y":0.36255866902582407},{"id":"clegg don w","label":"clegg don w","degree":2,"companies":["SMCI"],"x":0.0,"y":0.0}],"edges":[{"source":"kao george","target":"clegg don w","similarity":0.867489,"companies":["SMCI"]},{"source":"kao george","target":"weigand david e","similarity":0.748614,"companies":["SMCI"]},{"source":"weigand david e","target":"clegg don w","similarity":0.822426,"companies":["SMCI"]}]}