{"id":481,"nodes":[{"id":"gan david y.","label":"gan david y.","degree":2,"companies":["ACM"],"x":1.0,"y":1.0},{"id":"poloni lara","label":"poloni lara","degree":3,"companies":["ACM"],"x":0.6904243347907615,"y":0.21402959838361882},{"id":"kapoor gaurav","label":"kapoor gaurav","degree":3,"companies":["ACM"],"x":0.3116810464078913,"y":0.7880757828150341},{"id":"rudd troy","label":"rudd troy","degree":2,"companies":["ACM"],"x":0.0,"y":0.0}],"edges":[{"source":"gan david y.","target":"kapoor gaurav","similarity":0.73031,"companies":["ACM"]},{"source":"gan david y.","target":"poloni lara","similarity":0.7915,"companies":["ACM"]},{"source":"poloni lara","target":"kapoor gaurav","similarity":0.912202,"companies":["ACM"]},{"source":"poloni lara","target":"rudd troy","similarity":0.738412,"companies":["ACM"]},{"source":"kapoor gaurav","target":"rudd troy","similarity":0.749705,"companies":["ACM"]}]}