{"id":710,"nodes":[{"id":"shamburger julie","label":"shamburger julie","degree":2,"companies":["SBSI"],"x":0.16787328910576235,"y":1.0},{"id":"mccabe brian k","label":"mccabe brian k","degree":2,"companies":["SBSI"],"x":1.0,"y":0.36255866902582407},{"id":"gibson lee r","label":"gibson lee r","degree":2,"companies":["SBSI"],"x":0.0,"y":0.0}],"edges":[{"source":"shamburger julie","target":"gibson lee r","similarity":0.770783,"companies":["SBSI"]},{"source":"shamburger julie","target":"mccabe brian k","similarity":0.834851,"companies":["SBSI"]},{"source":"mccabe brian k","target":"gibson lee r","similarity":0.730254,"companies":["SBSI"]}]}