{"id":834,"nodes":[{"id":"agrawal kailas","label":"agrawal kailas","degree":2,"companies":["ID"],"x":0.16787328910576235,"y":1.0},{"id":"atwater mark","label":"atwater mark","degree":2,"companies":["ID"],"x":1.0,"y":0.36255866902582407},{"id":"ciappina antonino","label":"ciappina antonino","degree":2,"companies":["ID"],"x":0.0,"y":0.0}],"edges":[{"source":"agrawal kailas","target":"atwater mark","similarity":1.0,"companies":["ID"]},{"source":"agrawal kailas","target":"ciappina antonino","similarity":1.0,"companies":["ID"]},{"source":"atwater mark","target":"ciappina antonino","similarity":1.0,"companies":["ID"]}]}