{"id":215,"nodes":[{"id":"schroeder stephen l","label":"schroeder stephen l","degree":3,"companies":["WTI"],"x":0.42726905141058685,"y":0.5727466693282607},{"id":"gibbons john d","label":"gibbons john d","degree":1,"companies":["WTI"],"x":1.0,"y":0.0},{"id":"yang sunghee janet","label":"yang sunghee janet","degree":2,"companies":["WTI"],"x":0.07028081681580109,"y":0.6683580840673888},{"id":"murphy thomas p.","label":"murphy thomas p.","degree":2,"companies":["WTI"],"x":0.7407216666455397,"y":0.25928850333425163},{"id":"williford william j","label":"williford william j","degree":2,"companies":["WTI"],"x":0.0,"y":1.0},{"id":"krohn tracy w","label":"krohn tracy w","degree":2,"companies":["WTI"],"x":0.3117357387556396,"y":0.9496448284382158}],"edges":[{"source":"schroeder stephen l","target":"krohn tracy w","similarity":0.884384,"companies":["WTI"]},{"source":"schroeder stephen l","target":"murphy thomas p.","similarity":0.75,"companies":["WTI"]},{"source":"schroeder stephen l","target":"yang sunghee janet","similarity":0.75,"companies":["WTI"]},{"source":"gibbons john d","target":"murphy thomas p.","similarity":0.877945,"companies":["WTI"]},{"source":"yang sunghee janet","target":"williford william j","similarity":0.9,"companies":["WTI"]},{"source":"williford william j","target":"krohn tracy w","similarity":0.739695,"companies":["WTI"]}]}