{"id":130,"nodes":[{"id":"scaglione diego anthony","label":"scaglione diego anthony","degree":1,"companies":["ABM"],"x":0.8877993992625453,"y":1.0},{"id":"salmirs scott b","label":"salmirs scott b","degree":6,"companies":["ABM"],"x":0.5082957851232585,"y":0.5991687365966144},{"id":"gartland thomas m","label":"gartland thomas m","degree":4,"companies":["ABM"],"x":0.6250452829765502,"y":0.0},{"id":"chin dean a","label":"chin dean a","degree":1,"companies":["ABM"],"x":0.0,"y":0.9523190673520504},{"id":"webb winifred markus","label":"webb winifred markus","degree":5,"companies":["ABM"],"x":0.6500126163990566,"y":0.33462691517495924},{"id":"kesavan sudhakar","label":"kesavan sudhakar","degree":5,"companies":["ABM"],"x":0.4796080116619196,"y":0.1982161605756258},{"id":"chavez linda","label":"chavez linda","degree":4,"companies":["ABM"],"x":1.0,"y":0.2583403484086361},{"id":"newborn andrea r","label":"newborn andrea r","degree":4,"companies":["ABM"],"x":0.13447643541477303,"y":0.2598858419469533}],"edges":[{"source":"scaglione diego anthony","target":"salmirs scott b","similarity":0.751007,"companies":["ABM"]},{"source":"salmirs scott b","target":"chavez linda","similarity":0.722,"companies":["ABM"]},{"source":"salmirs scott b","target":"chin dean a","similarity":0.816176,"companies":["ABM"]},{"source":"salmirs scott b","target":"kesavan sudhakar","similarity":0.784783,"companies":["ABM"]},{"source":"salmirs scott b","target":"newborn andrea r","similarity":0.798864,"companies":["ABM"]},{"source":"salmirs scott b","target":"webb winifred markus","similarity":0.784783,"companies":["ABM"]},{"source":"gartland thomas m","target":"chavez linda","similarity":0.7,"companies":["ABM"]},{"source":"gartland thomas m","target":"kesavan sudhakar","similarity":0.777778,"companies":["ABM"]},{"source":"gartland thomas m","target":"newborn andrea r","similarity":0.836601,"companies":["ABM"]},{"source":"gartland thomas m","target":"webb winifred markus","similarity":0.888889,"companies":["ABM"]},{"source":"webb winifred markus","target":"chavez linda","similarity":0.8,"companies":["ABM"]},{"source":"webb winifred markus","target":"kesavan sudhakar","similarity":0.888889,"companies":["ABM"]},{"source":"webb winifred markus","target":"newborn andrea r","similarity":0.836601,"companies":["ABM"]},{"source":"kesavan sudhakar","target":"chavez linda","similarity":0.8,"companies":["ABM"]},{"source":"kesavan sudhakar","target":"newborn andrea r","similarity":0.717087,"companies":["ABM"]}]}