{"id":177,"nodes":[{"id":"nustad cynthia","label":"nustad cynthia","degree":6,"companies":["HMSY"],"x":0.6107893863942511,"y":1.0},{"id":"south teresa","label":"south teresa","degree":6,"companies":["HMSY"],"x":1.0,"y":0.6560988881632902},{"id":"neuman semone","label":"neuman semone","degree":6,"companies":["HMSY"],"x":0.3910554743989832,"y":0.0},{"id":"lucia william c","label":"lucia william c","degree":6,"companies":["HMSY"],"x":0.0,"y":0.34136305843732195},{"id":"sherman jeffrey scott","label":"sherman jeffrey scott","degree":6,"companies":["HMSY"],"x":0.49965653218357325,"y":0.5004983588223727},{"id":"aunan greg d","label":"aunan greg d","degree":6,"companies":["HMSY"],"x":0.10962305408434161,"y":0.8424032111450653},{"id":"williams douglas m.","label":"williams douglas m.","degree":6,"companies":["HMSY"],"x":0.889892077674589,"y":0.15712358694619863}],"edges":[{"source":"nustad cynthia","target":"aunan greg d","similarity":0.852028,"companies":["HMSY"]},{"source":"nustad cynthia","target":"lucia william c","similarity":0.81678,"companies":["HMSY"]},{"source":"nustad cynthia","target":"neuman semone","similarity":0.871962,"companies":["HMSY"]},{"source":"nustad cynthia","target":"sherman jeffrey scott","similarity":0.900164,"companies":["HMSY"]},{"source":"nustad cynthia","target":"south teresa","similarity":0.8363,"companies":["HMSY"]},{"source":"nustad cynthia","target":"williams douglas m.","similarity":0.843987,"companies":["HMSY"]},{"source":"south teresa","target":"aunan greg d","similarity":0.878744,"companies":["HMSY"]},{"source":"south teresa","target":"lucia william c","similarity":0.849001,"companies":["HMSY"]},{"source":"south teresa","target":"neuman semone","similarity":0.848987,"companies":["HMSY"]},{"source":"south teresa","target":"sherman jeffrey scott","similarity":0.948215,"companies":["HMSY"]},{"source":"south teresa","target":"williams douglas m.","similarity":0.948451,"companies":["HMSY"]},{"source":"neuman semone","target":"aunan greg d","similarity":0.808291,"companies":["HMSY"]},{"source":"neuman semone","target":"lucia william c","similarity":0.756886,"companies":["HMSY"]},{"source":"neuman semone","target":"sherman jeffrey scott","similarity":0.843487,"companies":["HMSY"]},{"source":"neuman semone","target":"williams douglas m.","similarity":0.866519,"companies":["HMSY"]},{"source":"lucia william c","target":"aunan greg d","similarity":0.815505,"companies":["HMSY"]},{"source":"lucia william c","target":"sherman jeffrey scott","similarity":0.882381,"companies":["HMSY"]},{"source":"lucia william c","target":"williams douglas m.","similarity":0.866844,"companies":["HMSY"]},{"source":"sherman jeffrey scott","target":"aunan greg d","similarity":0.911945,"companies":["HMSY"]},{"source":"sherman jeffrey scott","target":"williams douglas m.","similarity":0.975593,"companies":["HMSY"]},{"source":"aunan greg d","target":"williams douglas m.","similarity":0.905408,"companies":["HMSY"]}]}